orthanc_cache_plugin/__init__.py
orthanc_cache_plugin/server.py
orthanc_cache_plugin-0.0.1.dist-info/LICENSE
orthanc_cache_plugin-0.0.1.dist-info/WHEEL
orthanc_cache_plugin-0.0.1.dist-info/METADATA
orthanc_cache_plugin-0.0.1.dist-info/RECORD
