Metadata-Version: 2.1
Name: orthanc-cache-plugin
Version: 0.0.1
Summary: A plugin for Orthanc DICOM server to cache API responses
License: AGPL-3.0
Author: Benedict Panggabean
Author-email: holabenedict@gmail.com
Requires-Python: >=3.9,<4.0
Classifier: License :: OSI Approved :: GNU Affero General Public License v3
Classifier: Programming Language :: Python :: 3
Classifier: Programming Language :: Python :: 3.9
Classifier: Programming Language :: Python :: 3.10
Classifier: Programming Language :: Python :: 3.11
Requires-Dist: diskcache (>=5.4.0,<6.0.0)
Requires-Dist: pytz (>=2022.7.1,<2023.0.0)
